MANIFEST.in
README.rst
setup.py
admin_xtra_widgets/__init__.py
admin_xtra_widgets/urls.py
admin_xtra_widgets/views.py
admin_xtra_widgets/widgets.py
admin_xtra_widgets/locale/fr/LC_MESSAGES/django.mo
admin_xtra_widgets/locale/fr/LC_MESSAGES/django.po
django_admin_xtra_widgets.egg-info/PKG-INFO
django_admin_xtra_widgets.egg-info/SOURCES.txt
django_admin_xtra_widgets.egg-info/dependency_links.txt
django_admin_xtra_widgets.egg-info/not-zip-safe
django_admin_xtra_widgets.egg-info/top_level.txt