Metadata-Version: 1.1
Name: django-admin-xtra-widgets
Version: 0.1.1
Summary: more widgets for the django admin
Home-page: UNKNOWN
Author: Luc Jean
Author-email: ljean@apidev.fr
License: GNU LGPL
Platform: UNKNOWN
Classifier: Development Status :: 3 - Alpha
Classifier: Framework :: Django
Classifier: Environment :: Web Environment
Classifier: Intended Audience :: Developers
Classifier: License :: OSI Approved :: GNU Lesser General Public License v3 or later (LGPLv3+)
Classifier: Programming Language :: Python
Classifier: Operating System :: OS Independent
Classifier: Topic :: Software Development :: Libraries
